[
    {
        "Containers": -1,
        "Created": 1701416990,
        "Id": "sha256:b6548eacb0639263e9d8abfee48f8ac8b327102a05335b67572f715c580a968e",
        "Labels": {
            "org.opencontainers.image.ref.name": "ubuntu",
            "org.opencontainers.image.version": "22.04"
        },
        "ParentId": "",
        "RepoDigests": [
            "ubuntu@sha256:8eab65df33a6de2844c9aefd19efe8ddb87b7df5e9185a4ab73af936225685bb"
        ],
        "RepoTags": [
            "ubuntu:latest"
        ],
        "SharedSize": -1,
        "Size": 77849732,
        "VirtualSize": 77849732
    },
    {
        "Containers": -1,
        "Created": 1700557532,
        "Id": "sha256:a6bd71f48f6839d9faae1f29d3babef831e76bc213107682c5cc80f0cbb30866",
        "Labels": {
            "maintainer": "NGINX Docker Maintainers <docker-maint@nginx.com>"
        },
        "ParentId": "",
        "RepoDigests": [
            "nginx@sha256:10d1f5b58f74683ad34eb29287e07dab1e90f10af243f151bb50aa5dbb4d62ee"
        ],
        "RepoTags": [
            "nginx:latest"
        ],
        "SharedSize": -1,
        "Size": 186779305,
        "VirtualSize": 186779305
    },
    {
        "Containers": -1,
        "Created": 1696491212,
        "Id": "sha256:e4c58958181a5925816faa528ce959e487632f4cfd192f8132f71b32df2744b4",
        "Labels": {
            "org.opencontainers.image.ref.name": "ubuntu",
            "org.opencontainers.image.version": "22.04"
        },
        "ParentId": "",
        "RepoDigests": [
            "ubuntu@sha256:2b7412e6465c3c7fc5bb21d3e6f1917c167358449fecac8176c6e496e5c1f05f"
        ],
        "RepoTags": [],
        "SharedSize": -1,
        "Size": 77823855,
        "VirtualSize": 77823855
    },
    {
        "Containers": -1,
        "Created": 1695935967,
        "Id": "sha256:8ca4688f4f356596b5ae539337c9941abc78eda10021d35cbc52659c74d9b443",
        "Labels": null,
        "ParentId": "",
        "RepoDigests": [
            "alpine@sha256:eece025e432126ce23f223450a0326fbebde39cdf496a85d8c016293fc851978"
        ],
        "RepoTags": [
            "alpine:latest"
        ],
        "SharedSize": -1,
        "Size": 7335363,
        "VirtualSize": 7335363
    },
    {
        "Containers": -1,
        "Created": 1689722373,
        "Id": "sha256:a416a98b71e224a31ee99cff8e16063554498227d2b696152a9c3e0aa65e5824",
        "Labels": null,
        "ParentId": "",
        "RepoDigests": [
            "amjad123ali/dockur_fyp@sha256:023917ec6a886d0e8e15f28fb543515a5fcd8d938edb091e8147db4efed388ee"
        ],
        "RepoTags": [
            "amjad123ali/dockur_fyp:busybox"
        ],
        "SharedSize": -1,
        "Size": 4261566,
        "VirtualSize": 4261566
    },
    {
        "Containers": -1,
        "Created": 1685439129,
        "Id": "sha256:f9a80a55f492e823bf5d51f1bd5f87ea3eed1cb31788686aa99a2fb61a27af6a",
        "Labels": {
            "org.opencontainers.image.ref.name": "ubuntu",
            "org.opencontainers.image.version": "18.04"
        },
        "ParentId": "",
        "RepoDigests": [
            "ubuntu@sha256:152dc042452c496007f07ca9127571cb9c29697f42acbfad72324b2bb2e43c98"
        ],
        "RepoTags": [
            "ubuntu:18.04"
        ],
        "SharedSize": -1,
        "Size": 63156473,
        "VirtualSize": 63156473
    }
]